fcst_python_ieseg/__init__.py
fcst_python_ieseg/date_utils.py
tests/__init__.py
tests/test_date_utils.py
fcst_python_ieseg-0.1.3.dist-info/LICENSE
fcst_python_ieseg-0.1.3.dist-info/METADATA
fcst_python_ieseg-0.1.3.dist-info/WHEEL
fcst_python_ieseg-0.1.3.dist-info/top_level.txt
fcst_python_ieseg-0.1.3.dist-info/RECORD
